facereg/__init__.py
facereg/__main__.py
facereg/encodings.pickle
facereg/face_encoder.py
facereg/google_images.py
facereg/recognize_faces.py
facereg-0.2.1.2.dist-info/METADATA
facereg-0.2.1.2.dist-info/RECORD
facereg-0.2.1.2.dist-info/WHEEL
facereg-0.2.1.2.dist-info/top_level.txt
