Metadata-Version: 2.1
Name: facereg
Version: 0.2.1.2
Summary: Face recognition from identity cards with OpenCV and Deep Learning.
Home-page: https://github.com/verifid/facereg
Author: Abdullah Selek
Author-email: abdullahselek@gmail.com
Maintainer: Abdullah Selek
Maintainer-email: abdullahselek@gmail.com
License: MIT License
Download-URL: https://pypi.org/project/facereg
Keywords: deep learning,face recognition,face,opencv
Platform: Any
Classifier: Intended Audience :: Developers
Classifier: Intended Audience :: Science/Research
Classifier: License :: OSI Approved :: MIT License
Classifier: Operating System :: OS Independent
Classifier: Topic :: Software Development
Classifier: Topic :: Scientific/Engineering
Classifier: Programming Language :: Python
Classifier: Programming Language :: Python :: 2.7
Classifier: Programming Language :: Python :: 3.5
Classifier: Programming Language :: Python :: 3.6
Classifier: Programming Language :: Python :: 3.7
Requires-Python: >=2.7, !=3.0.*, !=3.1.*, !=3.2.*, !=3.3.*, !=3.4.*, <4
Requires-Dist: opencv-python
Requires-Dist: opencv-contrib-python
Requires-Dist: dlib
Requires-Dist: face-recognition
Requires-Dist: imutils
Requires-Dist: google-images-download
